smart_tools/__init__.py
smart_tools/aggregator/__init__.py
smart_tools/aggregator/fileaggregator.py
smart_tools/aggregator/main.py
smart_tools/aggregator/config/aggregator_config.yaml
smart_tools/banking/__init__.py
smart_tools/banking/bic.py
smart_tools/banking/iban.py
smart_tools/banking/main.py
smart_tools/banking/mtparty.py
smart_tools/banking/regex_patterns.py
smart_tools/banking/config/iban_config.yaml
smart_tools/banking/config/swift_regex_patterns.yaml
smart_tools/banking/swift/__init__.py
smart_tools/banking/swift/regex_patterns.py
smart_tools/common/__init__.py
smart_tools/common/database.py
smart_tools/common/dataframe.py
smart_tools/common/downloader.py
smart_tools/common/smartsys.py
smart_tools/common/sql.py
smart_tools/comparator/__init__.py
smart_tools/comparator/filecomparator.py
smart_tools/comparator/main.py
smart_tools/dissector/__init__.py
smart_tools/dissector/dfdissector.py
smart_tools/dissector/filedissector.py
smart_tools/dissector/main.py
smart_tools/dissector/config/dissector_config.yaml
smart_tools/fusioner/config/fusioner_config.toml
smart_tools/morpher/__init__.py
smart_tools/morpher/filemorpher.py
smart_tools/morpher/main.py
smart_tools/morpher/config/morpher_config.yaml
smart_tools-0.10.4.data/data/scripts/config/aggregator_config.yaml
smart_tools-0.10.4.data/data/scripts/config/dissector_config.yaml
smart_tools-0.10.4.data/data/scripts/config/fusioner_config.toml
smart_tools-0.10.4.data/data/scripts/config/iban_config.yaml
smart_tools-0.10.4.data/data/scripts/config/morpher_config.yaml
smart_tools-0.10.4.data/data/scripts/config/swift_regex_patterns.yaml
smart_tools-0.10.4.dist-info/LICENSE
smart_tools-0.10.4.dist-info/METADATA
smart_tools-0.10.4.dist-info/WHEEL
smart_tools-0.10.4.dist-info/entry_points.txt
smart_tools-0.10.4.dist-info/top_level.txt
smart_tools-0.10.4.dist-info/RECORD
