Metadata-Version: 2.2
Name: smart_tools
Version: 0.10.4
Summary: A variety of smart tools to make analytics easy
Home-page: https://github.com/arcot23/smart_tools
Author: Prabhuram Venkatesan
Author-email: arcot23@gmail.com
Project-URL: Homepage, https://pypi.org/project/smart-tools/
Project-URL: Repository, https://github.com/arcot23/smart_tools
Keywords: smart,tools,dissector,morpher,comparator,aggregator,fusioner,analysis,analyze,data
Classifier: Programming Language :: Python :: 3
Classifier: License :: OSI Approved :: MIT License
Classifier: Operating System :: OS Independent
Requires-Python: >=3.8
License-File: LICENSE
